{
  "docs": {
    "Getting Started": [
      "getting-started/quick-start"
    ],
    "Components": [
      {
        "type": "category",
        "collapsible": true,
        "collapsed": false,
        "label": "Desktop",
        "items": [
          "components/desktop/button",
          "components/desktop/checkbox",
          "components/desktop/dropdown",
          "components/desktop/multichoice",
          "components/desktop/notification",
          "components/desktop/radio-button",
          "components/desktop/spinner",
          "components/desktop/text",
          "components/desktop/textarea"
        ]
      },
      {
        "type": "category",
        "collapsible": true,
        "collapsed": false,
        "label": "Mobile",
        "items": [
          "components/mobile/mobile-button",
          "components/mobile/mobile-checkbox",
          "components/mobile/mobile-notification",
          "components/mobile/mobile-radio-button",
          "components/mobile/mobile-text",
          "components/mobile/mobile-textarea"
        ]
      }
    ],
    "Guides": [
      "guides/comparison-v0-v1",
      "guides/search-box-customization"
    ]
  },
  "release-notes": {
    "Releases": [
      "releases/release-notes",
      "releases/release-notes-v1.0.3",
      "releases/release-notes-v1.0.2",
      "releases/release-notes-v1.0.1",
      "releases/release-notes-v1.0.0"
    ]
  }
}
